{"KOTNumber":"KOT1013","table":"1","customerName":"Anas Jafry","customerMobile":"9884179675","stewardName":"STEWARD NAME","stewardCode":"STEWARD CODE","orderStatus":1,"date":"05-03-2018","timePunch":"1534","timeKOT":"","timeBill":"","timeSettle":"","cart":[{"name":"Darjeeling Salad","price":"30","isCustom":false,"code":"1005","qty":1},{"name":"Green Salad","price":"25","isCustom":false,"code":"1004","qty":1},{"name":"Onion Salad","price":"20","isCustom":false,"code":"1003","qty":1},{"name":"Veg Manchow Soup","price":"35","isCustom":false,"code":"2028","qty":1},{"name":"Hot & Sour Veg Soup","price":"35","isCustom":false,"code":"2026","qty":1},{"name":"Sharjah Milk Shake","price":"40","isCustom":false,"code":"4067","qty":1},{"name":"Papaya Milk Shake","price":"40","isCustom":false,"code":"4068","qty":2},{"name":"Banana Milk Shake","price":"40","isCustom":false,"code":"4070","qty":1},{"name":"Chicku Milk Shake","price":"40","isCustom":false,"code":"4071","qty":2},{"name":"Apple Milk Shake","price":"50","isCustom":false,"code":"4072","qty":1},{"name":"Mango Milk Shake","price":"60","isCustom":false,"code":"4079","qty":1}],"specialRemarks":"SPECIAL COMMENTS","extras":[{"name":"CGST","value":5,"unit":"PERCENTAGE","amount":24.75},{"name":"SGST","value":5,"unit":"PERCENTAGE","amount":24.75},{"name":"Service Charge","value":50,"unit":"FIXED","amount":50}],"discount":{}}